{
  "word_list": [
    "kulijo",
    "jan",
    "mute",
    "melome",
    "telo",
    "te",
    "poka",
    "a",
    "tan",
    "li",
    "mani",
    "lili",
    "wekama",
    "ala",
    "sijelo",
    "wasoweli",
    "kijetesantakalu",
    "kon",
    "taso",
    "supa",
    "kipisi",
    "sona",
    "nena",
    "alasa",
    "jasima",
    "nasin",
    "pini",
    "mije",
    "mijomi",
    "kokosila",
    "jonke",
    "lete",
    "ilo",
    "musi",
    "wile",
    "wan",
    "kule",
    "taki",
    "lupa",
    "meli",
    "waso",
    "meso",
    "insa",
    "pona",
    "lipu",
    "mulapisu",
    "kama",
    "ojuta",
    "la",
    "teje",
    "toki",
    "po",
    "akesi",
    "pika",
    "n",
    "suli",
    "omekapo",
    "konwe",
    "en",
    "monsi",
    "mi",
    "seme",
    "ijo",
    "nanpa",
    "jelo",
    "linja",
    "san",
    "ko",
    "lon",
    "kiwen",
    "penpo",
    "nasa",
    "pakala",
    "kili",
    "lanpan",
    "lape",
    "ku",
    "misikeke",
    "jaki",
    "moli",
    "nimi",
    "ken",
    "majuna",
    "leko",
    "kepeken",
    "ante",
    "sin",
    "olin",
    "unu",
    "su",
    "oko",
    "epiku",
    "walo",
    "len",
    "isipin",
    "soto",
    "tenpo",
    "pakola",
    "anu",
    "wa",
    "laso",
    "namako",
    "utala",
    "apeja",
    "suwi",
    "mun",
    "moku",
    "pimeja",
    "open",
    "tawa",
    "ale",
    "puwa",
    "usawi",
    "uta",
    "wuwojiti",
    "sinpin",
    "luka",
    "wawa",
    "pake",
    "weka",
    "sama",
    "misa",
    "ma",
    "unpa",
    "kalama",
    "nimisin",
    "mu",
    "selo",
    "monsuta",
    "e",
    "kasi",
    "anpa",
    "sike",
    "palisa",
    "mama",
    "pipi",
    "sewi",
    "oke",
    "pan",
    "yupekosi",
    "to",
    "pilin",
    "lawa",
    "kulupu",
    "linluwi",
    "esun",
    "poki",
    "kin",
    "seli",
    "jami",
    "tu",
    "suno",
    "ni",
    "ali",
    "sitelen",
    "sutopatikuna",
    "kiki",
    "pi",
    "nja",
    "powe",
    "kute",
    "owe",
    "tonsi",
    "soweli",
    "ona",
    "awen",
    "pana",
    "o",
    "kamalawala",
    "noka",
    "sina",
    "lukin",
    "loje",
    "soko",
    "pu",
    "kapesi",
    "pali",
    "kala",
    "ike",
    "jo",
    "tomo"
  ],
  "commentary": {
    "a": "I vanlig användning (både före och efter pu), är \"a\" och \"kin\" separata ord, var och en med sin egen mening. I pu betraktas de som synonymer.",
    "akesi": "akesi brukade betyda \"ogulligt djur\", och definieras på detta sätt i pu, men den definitionen föll ur bruk och togs senare bort i pu-kommentarerna som publicerades med ku.",
    "ala": "",
    "alasa": "I vissa sammanhang är användningen av \"alasa\" som ett förverb i betydelsen \"att försöka\" lika stor eller till och med större än \"lukin\". I pu har bara \"lukin\"/\"oko\" den betydelsen.",
    "ale": "\"ali\" är ett alternativ till \"ale\", myntat i en enkät 2002 för att undvika förvirring med \"ala\". Användningen av \"ale\" i stället för \"ali\" är dock fortfarande vanligare.\nMajoriteten av talarna säger att de inte förstår \"riklig, överflödig\" innebörden, åtminstone utan sammanhang.\n\"20, 120\" var icke-pu betydelser som tidigare användes tillsammans med 100; de är praktiskt taget okända nuförtiden.",
    "ali": "\"ali\" is an alternative to \"ale\", coined in a poll in 2002 in order to avoid confusion with \"ala\". However, the usage of \"ale\" over \"ali\" has been more common since at least the release of pu. Generally not considered a word in its own right.",
    "anpa": "In common usage (both before and after pu), \"anpa\" has the meaning of \"place that is down\". In pu, \"noka\" has that meaning instead.",
    "ante": "",
    "anu": "The usage of \"anu\" as a content word meaning \"choose\" remains controversial.",
    "apeja": "According to jan Sonja, \"apeja\" never appeared in any pre-pu toki pona dictionary made by her and never promoted by her, instead it may have been \"just an experimental idea in a forum post\".",
    "awen": "",
    "e": "",
    "en": "There are various analyses of the syntactic role of \"en\". Originally intended to be used as \"and\", it was changed (via poll in 2002) to just be used with \"head nouns\". One of the more recent analyses (including 2021's April Fools) treats \"en\" as a subject marker.",
    "epiku": "",
    "esun": "According to jan Sonja, \"esun was told [to her] by a taxi driver who spoke a language from the Akan family in West Africa\".",
    "ijo": "",
    "ike": "",
    "ilo": "",
    "insa": "",
    "isipin": "",
    "jaki": "",
    "jami": "Often used for \"stim\".",
    "jan": "There are two sides to the concept, \"sentient entity\" and \"homo sapiens\", which matters for whether to use the word in edge cases (i.e. aliens, humans turned into werewolves, etc). Which sense is more central to the word remains controversial.",
    "jasima": "",
    "jelo": "Some extend \"jelo\" to include lime green, but this usage is uncommon.",
    "jo": "",
    "jonke": "Coined in reference to the Untitled Goose Game fandom.",
    "kala": "",
    "kalama": "",
    "kama": "",
    "kamalawala": "The word is from a story called \"jan pi Kamalawala\". A character's name is described as \"nimi Jan pi Kama e Lawa Ala\", and a shortened version given as \"nimi Kamalawala\". jan Kipo is responsible for it becoming a word instead of just a name.",
    "kapesi": "",
    "kasi": "",
    "ken": "",
    "kepeken": "Whether \"kepeken\" should be used with or without \"e\" in a predicative position (meaning \"to use\") remains controversial.",
    "kijetesantakalu": "Coined as an April Fools joke in 2009.",
    "kiki": "The word is loaned from the 2001 Vilanyur S Ramachandran & Edward Hubbard version of Wolfgang Köhler's 1912 psycholinguistic experiment. The experiment studied sound symbolism on the words \"bouba\" and \"kiki\".",
    "kili": "In post-ku 2021, metaphorical definitions for kili have been suggested, including but not limited to \"offspring\" and \"product\", and are moderately popular. It is not yet clear whether this will remain in use long-term.",
    "kin": "In common usage (both before and after pu), \"a\" and \"kin\" are separate words, each with their own meaning. In pu, they are considered synonyms.\nUnderwent significant changes in usage in 2002, alongside \"en\" and (now obsolete) \"kan\".",
    "kipisi": "",
    "kiwen": "This word was coined in a poll in 2002, replacing the compound phrase \"wawa ma\".",
    "ko": "The \"clinging form\" definition was elaborated to mean \"a shape or mass that sticks or clings; a clot, a thick or viscous lump, a clump that can be reshaped\".",
    "kokosila": "In Esperanto, \"krokodili\" means \"to speak among Esperantists in a language besides Esperanto,\" and is an established bit of Esperanto culture.",
    "kon": "",
    "konwe": "Conway hänvisar till John Horton Conway, skapare av den cellulära automatan Game of Life.\n\"konwe\"s avsedda betydelse sträcker sig bortom bara \"levande\" och \"liv\". Den kan användas för att beskriva stenar eller floder eller andra icke-levande saker",
    "ku": "Se den officiella Toki Pona-hemsidan för sätt att köpa boken.",
    "kule": "in addition to its pu-definitions, kule is sometimes used to talk about more general kinds of categories, like type, kind, flavour, gender, etc.",
    "kulijo": "",
    "kulupu": "",
    "kute": "",
    "la": "",
    "lanpan": "",
    "lape": "",
    "laso": "",
    "lawa": "",
    "leko": "",
    "len": "",
    "lete": "",
    "li": "",
    "lili": "",
    "linja": "",
    "linluwi": "",
    "lipu": "",
    "loje": "",
    "lon": "",
    "luka": "",
    "lukin": "In common usage (both before and after pu), \"lukin\" and \"oko\" are separate words, each with their own meaning. In pu, they are considered synonyms. Those who consider them synonyms typically don't use \"oko\" at all, preferring \"lukin\" in all circumstances. The usage of \"alasa\" as a preverb meaning \"try to\" is more common than \"lukin\". In pu, only \"lukin\" has this meaning. A very common beginner mistake is treating \"lukin\" as if it means \"appearance\", due to the mistakenly equating the \"visual\" meaning as in \"pona lukin (visually good)\" to mean \"looks good\".",
    "lupa": "",
    "ma": "",
    "majuna": "",
    "mama": "",
    "mani": "",
    "meli": "",
    "melome": "",
    "meso": "",
    "mi": "",
    "mije": "",
    "mijomi": "",
    "misa": "",
    "misikeke": "The word was used privately by jan Sonja up until November 2019, when she mentioned it in the ma pona pi toki pona discord server as a word she was experimenting with. It is believed the word was originally coined in 2007-2009 alongside pan, esun, apeja, monsuta, and pu, but this cannot be proven.",
    "moku": "",
    "moli": "",
    "monsi": "",
    "monsuta": "",
    "mu": "",
    "mulapisu": "",
    "mun": "",
    "musi": "",
    "mute": "",
    "n": "",
    "namako": "In common usage (both before and after pu), \"sin\" and \"namako\" are separate words, each with their own meaning. In pu, they are considered synonyms. Those who consider them synonyms typically don't use \"namako\" at all, preferring \"sin\" in all circumstances.",
    "nanpa": "",
    "nasa": "",
    "nasin": "",
    "nena": "",
    "ni": "",
    "nimi": "",
    "nimisin": "Mostly used in conversations in English. Likely was popularised by the :nimisin: emote in ma pona, which was originally used to notify Atawan (maintainer of \"nimi ale\") about newly coined words. In common speech, the meaning got extended to include most or all non-pu words, regardless if they were coined recently or not.",
    "nja": "",
    "noka": "noka can also mean any action involving the foot or leg, e.g. to kick, to step on, to touch with the leg.",
    "o": "",
    "ojuta": "",
    "oke": "",
    "oko": "In common usage (both before and after pu), \"lukin\" and \"oko\" are separate words, each with their own meaning. In pu, they are considered synonyms. Those who consider them synonyms typically don't use \"oko\" at all, preferring \"lukin\" in all circumstances, though some speakers do the opposite and use \"oko\" exclusively instead.",
    "olin": "In english, \"love\" can be used to mean \"like a lot\", but in toki pona, \"olin\" doesn't work that way. It indicates an emotional connection or bond, not preference",
    "omekapo": "Coined by jan Maliku in reference to the message \"o moku e kala pona\", which jan Sonja wrote on their copy of Toki Pona: The Language of Good during a Texas meetup.",
    "ona": "This word was coined in a poll in 2002. It replaced \"iki\", which was deemed too similar-sounding to \"ike\". Other options in the poll included \"ipi\" and \"i\".",
    "open": "Some proficient speakers use open as a preverb that means \"start to,\" that goes along with the complimentary pini preverb \"to stop\"",
    "owe": "",
    "pakala": "",
    "pake": "",
    "pakola": "",
    "pali": "",
    "palisa": "",
    "pan": "",
    "pana": "",
    "penpo": "Myntad med hänvisning till ma pona pi toki ponas \"tenpo pi toki pona taso\"-event, och förkortat till \"tenpo penpo\".",
    "pi": "The usage of \"pi\" to mean \"of\" (marking a possessor) is heavily discouraged nowadays, preferring it to only be used for regrouping within phrases.",
    "pika": "",
    "pilin": "",
    "pimeja": "",
    "pini": "Some proficient speakers use pini as a preverb that means \"to stop,\" that goes along with the complimentary open preverb \"start to\"",
    "pipi": "",
    "po": "",
    "poka": "",
    "poki": "poki is sometimes used as \"category\" or to express types of things. One example is roles or groups, in discord chat contexts",
    "pona": "",
    "powe": "",
    "pu": "Se den officiella Toki Pona-hemsidan för sätt att köpa boken.",
    "puwa": "",
    "sama": "",
    "san": "More popular than the synonymous (and older) tuli.\nsan was also part of a set of 10 digit words created by jan Lenoka: lenke, jatu, ini, san, se, nun, loku, take, patu, kajo (0 through 9). All of these coinages except for san lack notability to be included in the main dictionary. They can be found in the sandbox.",
    "seli": "In pu, definitions of seli are described as adjectives. ku's pu corrections clarify that these refer to nouns instead.",
    "selo": "",
    "seme": "",
    "sewi": "",
    "sijelo": "",
    "sike": "",
    "sin": "In common usage (both before and after pu), \"sin\" and \"namako\" are separate words, each with their own meaning. In pu, they are considered synonyms. Those who consider them synonyms typically don't use \"namako\" at all, preferring \"sin\" in all circumstances.",
    "sina": "",
    "sinpin": "",
    "sitelen": "",
    "soko": "",
    "sona": "",
    "soto": "",
    "soweli": "",
    "su": "This word was originally coined in ku as a reserved word for jan Sonja's future use. It was redefined upon the release of the first su book, making its status as a ku word debatable.",
    "suli": "",
    "suno": "",
    "supa": "",
    "sutopatikuna": "Coined by Alexandre Baudry in 2009 in response to jan Sonja coining \"kijetesantakalu\" as part of 2009's April Fools.",
    "suwi": "",
    "taki": "",
    "tan": "",
    "taso": "Some proficient speakers use taso as a connector between sentences (X taso Y), similar to \"X, but Y,\" as though taso behaved like la grammatically.",
    "tawa": "",
    "te": "May be paired with \"to\", or used on its own. It is unclear how accepted either approach is among te / to users.",
    "teje": "",
    "telo": "",
    "tenpo": "",
    "to": "May be paired with \"te\", or used on its own. It is unclear how accepted either approach is among te / to users.",
    "toki": "",
    "tomo": "",
    "tonsi": "* - Broader in meaning, somewhat less commonly accepted.\nWidely regarded in the community to be a crucial addition to toki pona. Occasionally referred to as an \"honorary pu word\" to highlight its status, or equated to a pu word outright.",
    "tu": "",
    "unpa": "Also defined as \"have marital relations with\" in pu; removed due to potential confusion.",
    "unu": "",
    "usawi": "Originally, usawi also included \"technology so complex it's impossible to tell apart from magic\" in its meaning, but this meaning has been deprecated by the creator.",
    "uta": "The dot in the \"uta\" sitelen pona is to distinguish luka-uta from moku.",
    "utala": "",
    "wa": "Ses ibland som en variant av \"a\".",
    "walo": "",
    "wan": "",
    "waso": "",
    "wasoweli": "First used as the name for a species in a mod for Caves of Qud created by akesi kon Nalasuni. Later appeared in ku as exclusively part of a translation for \"penguin\".",
    "wawa": "",
    "weka": "",
    "wekama": "",
    "wile": "",
    "wuwojiti": "May be seen not as a word in toki pona, but as a kind of memorisation tool in English to refer to the \"banned\" syllables. Occasionally extended to wuwojitinmanna to include the illegal consecutive nasal consonants.",
    "yupekosi": "Coined as a random keystroke. It is presumed jan Sonja used \"y\" by mistake, but then made it part of the joke by adding \"nobody knows how to pronounce the y\"."
  },
  "definitions": {
    "a": "(interjektion) aha, oh, ha, öh, eh, oj; (partikel) [kommer efter något för betoning eller som känsla]",
    "akesi": "reptil, groddjur, djur med fjäll, djur som kryper",
    "ala": "inte, inget, nej; (partikel) [negerar ett ord eller en fras]; (partikel) [bildar en ja-eller-nejfråga]; (siffra) noll",
    "alasa": "jaga, plocka (bär, svamp, etc.), samla, leta efter, försök; (pv.) att försöka",
    "ale": "allt, alla, varje, helhet, universum; (siffra) ett hundra",
    "ali": "[uttalsvariant av ale]",
    "anpa": "botten, undersida; under, nedanför; besegrad, ödmjuk, lågmäld",
    "ante": "annorlunda, förändrad; ändra, förändra, modifiera; annan, skillnad",
    "anu": "(partikel) [separerar flera möjligheter, ersätter en annan partikel], eller",
    "apeja": "skuld, skam, undvika, stigma; att anklaga, att peka ut, att avslöja, att vanära, att genera",
    "awen": "stanna, vänta, pausa; skydda, beskydda; fortsätta; (pv.) att fortsätta",
    "e": "(partikel) [markerar början på ett direkt objekt]",
    "en": "(partikel) [separerar flera subjekt]",
    "epiku": "episk, häftig cool, otrolig, fantastisk",
    "esun": "handel, byteshandel, utbyte, köpa, sälja; marknad, affär, mässa, basar, affärsplats",
    "ijo": "sak, ting, objekt, enhet, varelse, materia, fenomen",
    "ike": "av negativ kvalitet, t.ex. dålig, obehaglig, skadlig, onödig",
    "ilo": "redskap, maskin, enhet",
    "insa": "insida, center, mellan, mitt, mittpunkt, intern, inre",
    "isipin": "att tänka, brainstorma, rationalisera, dra slutsats, fundera",
    "jaki": "äckligt, orent, ohygieniskt, giftigt, motbjudante, ruttet",
    "jami": "mums; framkalla eller stimulera en positiv sensorisk upplevelse",
    "jan": "människa, person, någon",
    "jasima": "reflektera, eko; spegel, dubblett",
    "jelo": "gul, bärnstensfärgad, gyllene, limegult, orangegul",
    "jo": "hålla, bära, äga, innehålla",
    "jonke": "\"hjönk\", gåsljud, gås",
    "kala": "fisk, marint djur, havsdjur, simmande varelser",
    "kalama": "Att ge ifrån sig ljud; ljud, t.ex. sjunga, åska, trumma, klappa, skratta, pip",
    "kama": "arriving, coming, future, summoned; (preverb) to become, manage to, succeed in",
    "kamalawala": "anarki, uppror, revolt",
    "kapesi": "brun, grå, beige",
    "kasi": "växt, vegetation, ört, löv",
    "ken": "kan, får, förmåga, tillåtelse; möjlighet, kanske; tillåta, göra möjlig; (pv.) att kunna",
    "kepeken": "(preposition) använda, med hjälp av",
    "kijetesantakalu": "tvättbjörn, veckelbjörn (kinkajou); något djur i familjen Halvbjörnar (Procyonidae); något djur i överfamiljen Musteloidea",
    "kiki": "taggig, vass; vinkel, spets; trekantig",
    "kili": "frukt, grönsak, svamp",
    "kin": "(particle) [after phrase or at sentence start] too, also, as well, additionally",
    "kipisi": "split, cut, slice; piece, part; sharp, pointy",
    "kiwen": "hard object e.g. metal, stone, wood",
    "ko": "semi-solid, e.g. paste, powder, goo, sand, soil, clay; squishy, moldable; sticky",
    "kokosila": "att prata något annat språk än Toki Pona i ett sammanhang där Toki Pona hade varit mer lämpligt",
    "kon": "air, breath, wind; essence, spirit, soul, ghost; unseen agent",
    "konwe": "animacitet, liv; autonom varelse, levande ting, organism; levande, dynamisk; att ge liv åt, att väcka liv i",
    "ku": "interacting with the book Toki Pona Dictionary (2021) by Sonja Lang",
    "kule": "color, pigment; category, genre, flavor; colorful, diverse",
    "kulijo": "(interjection) [casually express appreciation or acknowledgement]; cool, fine, okay",
    "kulupu": "group, community, society, company, nation, collection, team, crowd",
    "kute": "ear, hearing organ; hear, listen, pay attention to, obey",
    "la": "(particle) [mark the previous statement as context to the following statement]",
    "lanpan": "take, seize, steal",
    "lape": "sleep, rest, break from an activity or work",
    "laso": "turquoise, blue, green, cyan, indigo, lime green",
    "lawa": "head, mind, brain; control, lead, guide; government, leader; rule, law",
    "leko": "square, cube, block, blocky object e.g. bricks, stairs",
    "len": "cloth, clothing, fabric, textile; covered, hidden, secret, private",
    "lete": "cold, cool, frozen; freeze, chill; raw, uncooked",
    "li": "(particle) [marks the start of an indicative verb (statement)]",
    "lili": "small, short, young; few; piece, part",
    "linja": "long, flexible thing, e.g. rope, yarn, hair, fur, line, strand",
    "linluwi": "bonded things which are stronger through their bonds e.g. network, internet, connection; weave, braid, interlace",
    "lipu": "flat and bendable object, e.g. paper, card, leaf; written text or document, e.g. book, website, clay tablet",
    "loje": "red, magenta, scarlet, pink, rust-colored, reddish orange",
    "lon": "present, existing, real, true; (preposition) located at, in, during, in the context of",
    "luka": "hand, arm, tactile limb, grasping limb; to grasp, interact with, feel using touch; (number) five",
    "lukin": "see, look, view, examine, read, watch; visual; eye, seeing organ; (preverb) try to",
    "lupa": "hole, pit, cave, doorway, window, portal",
    "ma": "earth, land, soil; country, territory, world; outdoors",
    "majuna": "gammal, åldrad, uråldrig",
    "mama": "parent, ancestor; creator, originator; caretaker, sustainer, guardian",
    "mani": "money, currency; thing of value e.g. gold, investment, livestock",
    "meli": "woman, female, feminine person, wife, girlfriend",
    "melome": "lesbian, sapphic, WLW",
    "meso": "medelpunkt, medium, medioker, medelmåttig; varken det ena eller det andra",
    "mi": "(pronoun) I, me, we, us",
    "mije": "man, male, masculine person, husband, boyfriend",
    "mijomi": "gay, achillean, MLM",
    "misa": "gruppen Glires (gnagare och hardjur) eller Eulipotyphla (äkta insektsätare); råtta, mus, ekorre, kanin, gnagare {~ suli} kapybara",
    "misikeke": "medical item or practice e.g. prescriptions, meditation, exercise, bandages, therapy",
    "moku": "eat, drink, consume, swallow, ingest; food, edible thing",
    "moli": "death, dead, die, dying; kill, murder",
    "monsi": "bak, baksida",
    "monsuta": "fear, nervousness, dread; scary, frightening; scary thing e.g. predator, threat, danger",
    "mu": "(animal noise or communication, onomatopoeia)",
    "mulapisu": "pizza",
    "mun": "moon, night sky object, star, celestial body",
    "musi": "fun, game, entertainment, art, play, amusing, interesting, comical, silly",
    "mute": "many, several, very; quantity; (number) twenty",
    "n": "(interjection) hm, uh, mm, er, umm, [indicate thinking or pause]",
    "namako": "spice, ornament, adornment; extra, additional",
    "nanpa": "number; (particle) [ordinal number], -th",
    "nasa": "strange, unusual, silly, abnormal, unexpected; drunk, intoxicated",
    "nasin": "method, doctrine, tradition; path, road, way",
    "nena": "protuberances e.g. bump, button, hill, nose",
    "ni": "this, that, these, those",
    "nimi": "word, name",
    "nimisin": "alla icke-pu ord; alla nya ord; alla skämtord",
    "nja": "meow, cat sound",
    "noka": "foot, leg, organ of locomotion, roots",
    "o": "(particle) [marks the end of a vocative (who is being spoken to)], [marks the start of an imperative (command, wish, instruction)], should",
    "ojuta": "adaptation of the English meme \"ligma\", (literally) \"o uta\" (lick)",
    "oke": "(bekräftelse eller accepterande)",
    "oko": "see, look, view, examine, read, watch; visual; eye, seeing organ; (preverb) try to",
    "olin": "to have a strong emotional bond with, e.g. affection, appreciation, compassion, respect; platonic, romantic, or familial relationships",
    "omekapo": "goodbye, farewell, see you later, (literally) \"o moku e kala pona\" (eat a good fish)",
    "ona": "(third-person pronoun) he, she, it, they",
    "open": "begin, start, open, turn on; beginning",
    "owe": "totalitarian, Orwellian; of or relating to Big Brother from the book Ninety Eighty-Four",
    "pakala": "damaged, broken, botched, harmed, messed up; mistake",
    "pake": "stoppa, avbryta; att blockera; att förhindra",
    "pakola": "[felstavning av pakala]",
    "pali": "work, activity; create, build, design; put effort toward, take action on",
    "palisa": "long and hard thing e.g. branch, pole, rod, stick, spine, mast",
    "pan": "grains, starchy foods, baked goods e.g. rice, sorghum, bread, noodles, masa, porridge, injera",
    "pana": "att ge, skicka, avge, förse, ställa, släppa",
    "penpo": "(likvärdig med \"(pi) toki pona taso\")",
    "pi": "(particle) [group the following words into one modifier for the previous word]",
    "pika": "elektrisk, elektronisk, ledande, mekanisk, online; elektricitet, blixt, åska, nätverk",
    "pilin": "experience e.g. emotion, feeling, touch; heart (physical or emotional)",
    "pimeja": "dark, unlit; dark color, e.g. black, purple, brown",
    "pini": "finish, stop, prevent; close, disable, turn off; ended, past; edge, end, conclusion",
    "pipi": "insect, bug, spider, tiny crawling creature",
    "po": "(number) four",
    "poka": "hip, side; next to, nearby, vicinity",
    "poki": "container e.g. bag, bowl, box, cup, cupboard, drawer, folder",
    "pona": "positive quality, e.g. good, pleasant, helpful, friendly, useful, peaceful",
    "powe": "overklig, falsk; låtsas; lura",
    "pu": "interacting with the book Toki Pona: The Language of Good by Sonja Lang",
    "puwa": "fluffig, mjuk (något som kan bli ihoptryckt och kommer försöka återgå till sin ursprungliga form)",
    "sama": "same, similar, alike; (adjective) peer, fellow, each other; (preposition) similar to, same as",
    "san": "(number) three",
    "seli": "hot, warm; heat, fire, flame; burn",
    "selo": "outer layer, e.g. skin, peel, shell, bark; outer shape, outer form, boundary",
    "seme": "(particle) [indicate a question by marking missing info in a sentence]; what, which, who",
    "sewi": "up, top, above, highest part; divine, sacred, supernatural; awesome, inspiring, excelling",
    "sijelo": "body, shape, physical state, torso, substance, form",
    "sike": "circle, sphere, spiral, round thing e.g. ball, wheel; repeating thing e.g. cycle, orbit, loop",
    "sin": "new, fresh, update; repeat, do again",
    "sina": "(pronoun) you, y'all",
    "sinpin": "vertical surface e.g. wall, board; front of something e.g. face",
    "sitelen": "bild, fotografi, avbildning, symbol, tecken, skrift",
    "soko": "mushroom, fungus, lichen",
    "sona": "knowledge, information, data; know, be skilled in, be wise about; (preverb) know how to",
    "soto": "vänster, vänstra sidan, babord",
    "soweli": "fuzzy creature, land animal, beast",
    "su": "interagera med en bok ur Sonja Langs illustrerade bokserie, som började med Trollkarlen från Oz",
    "suli": "big, heavy, large, long, tall, wide; important, relevant",
    "suno": "light, shine, glow, radiance; sun, light source; brightness",
    "supa": "flat horizontal surface, especially to put or rest things on e.g. bed, floor, desk, plate, table, platform, stage",
    "sutopatikuna": "näbbdjur",
    "suwi": "sweet, fragrant; cute, adorable",
    "taki": "klibbigt, magnetiskt; förbindelse, attrahera, fästa, gem",
    "tan": "(preposition) from, because of; cause, origin",
    "taso": "only, exclusively; (particle) [marks a sentence as qualifying or contradictory], but, however",
    "tawa": "motion, e.g. walking, shaking, flight, travel; (preposition) to, for, going to, from the perspective of",
    "te": "(particle) [opens a quote]",
    "teje": "höger, höger sida, styrbord",
    "telo": "liquids e.g. water, gasoline, soda, lava, soup, oil, ink",
    "tenpo": "tid, händelse, situation, tillfälle, period, varaktighet",
    "to": "(particle) [closes a quote]",
    "toki": "communicate, say, think; conversation, story; language",
    "tomo": "indoor space or shelter e.g. room, building, home, tent, shack",
    "tonsi": "nonbinary, gender nonconforming, genderqueer, transgender*",
    "tu": "(number) two; separate, divide, split",
    "unpa": "sex, to have sex with",
    "unu": "lila, violett",
    "usawi": "magi, häxkonst, trolldom; förtrollad, magisk, övernaturlig, ockult, oförståligt",
    "uta": "mun, läppar, hals, konsumerande öppning",
    "utala": "kämpa, tävla, strida; tävling, utmaning; kamp, strävan",
    "wa": "(interjektion) [visar vördnad eller häpnad]",
    "walo": "ljusfärgad, vit, blek, ljusgrå",
    "wan": "(siffra) ett; singular; kombinera, sammanfoga, blanda, smälta samman",
    "waso": "fågel, flygande djur, bevingat djur",
    "wasoweli": "djur med egenskaper av både waso och soweli",
    "wawa": "kraft, energi, styrka; självsäker, intensiv, kraftfull; fantastisk, imponerande",
    "weka": "frånvarande, borta, avlägsen; ta bort, bli av med",
    "wekama": "lämna och komma tillbaka, vara temporärt frånvarande med avsikten att återvända",
    "wile": "vilja, önskan, krav; (pv.) vill",
    "wuwojiti": "att använda en eller fler av de förbjudna stavelserna wu, wo, ji eller ti; att bryta mot Toki Ponas fonotax",
    "yupekosi": "att uppföra sig som George Lucas och revidera dina gamla kreativa verk och faktiskt göra dem sämre"
  },
  "etymology": {
    "a": [
      {
        "language": "onomatopoetiskt"
      }
    ],
    "akesi": [
      {
        "definition": "ödla",
        "language": "Nederländska"
      }
    ],
    "ala": [
      {
        "definition": "nej",
        "language": "Georgiska"
      }
    ],
    "alasa": [
      {
        "definition": "jakt, (bokstavligen) på jakt",
        "language": "Akadisk franska"
      }
    ],
    "ale": [
      {
        "definition": "allt",
        "language": "Nederländska"
      }
    ],
    "ali": [
      {
        "definition": "allt",
        "language": "Nederländska"
      }
    ],
    "anpa": [
      {
        "definition": "under",
        "language": "Akadisk franska"
      }
    ],
    "ante": [
      {
        "definition": "annat, annorlunda",
        "language": "Nederländska"
      }
    ],
    "anu": [
      {
        "definition": "eller",
        "language": "Georgiska"
      }
    ],
    "apeja": [
      {
        "definition": "skam, vanhedra vanära",
        "language": "Finska"
      }
    ],
    "awen": [
      {
        "definition": "keep, care for, hold (in a particular state)",
        "language": "Nederländska"
      }
    ],
    "e": [
      {
        "language": "a priori"
      }
    ],
    "en": [
      {
        "definition": "and",
        "language": "Nederländska"
      }
    ],
    "epiku": [
      {
        "definition": "epic",
        "language": "Franska"
      }
    ],
    "esun": [
      {
        "language": "Akan",
        "definition": "at market"
      }
    ],
    "ijo": [
      {
        "definition": "something",
        "language": "Esperanto"
      },
      {
        "definition": "(relative pronoun root)",
        "language": "Romance"
      }
    ],
    "ike": [
      {
        "definition": "bad, mean, wicked",
        "language": "Finska"
      }
    ],
    "ilo": [
      {
        "definition": "tool",
        "language": "Esperanto"
      },
      {
        "definition": "(agent suffix)",
        "language": "German"
      }
    ],
    "insa": [
      {
        "definition": "inside, center, stomach",
        "language": "Tok Pisin"
      },
      {
        "definition": "inside",
        "language": "Engelska"
      }
    ],
    "isipin": [
      {
        "definition": "to think",
        "language": "Tagalog"
      }
    ],
    "jaki": [
      {
        "definition": "yucky",
        "language": "Engelska"
      }
    ],
    "jami": [
      {
        "definition": "yummy",
        "language": "Engelska"
      }
    ],
    "jan": [
      {
        "definition": "person",
        "language": "Kantonesiska"
      }
    ],
    "jasima": [
      {
        "definition": "to reflect, reverberate",
        "language": "Turkiska"
      }
    ],
    "jelo": [
      {
        "definition": "gul",
        "language": "Engelska"
      }
    ],
    "jo": [
      {
        "definition": "have",
        "language": "Mandarin"
      }
    ],
    "jonke": [
      {
        "definition": "hjönk",
        "language": "onomatopoetiskt"
      }
    ],
    "kala": [
      {
        "definition": "fish",
        "language": "Finska"
      }
    ],
    "kalama": [
      {
        "definition": "noise (of the human voice)",
        "language": "Serbokroatiska"
      }
    ],
    "kama": [
      {
        "definition": "event, arrive, happen, become, bring about, summon",
        "language": "Tok Pisin"
      }
    ],
    "kamalawala": [
      {
        "definition": "'arrival of no government', the beginning of anarchy",
        "language": "toki pona"
      }
    ],
    "kapesi": [
      {
        "definition": "brown, coffee (colour)",
        "language": "Kantonesiska"
      },
      {
        "definition": "brown, coffee (colour)",
        "language": "Mandarin"
      }
    ],
    "kasi": [
      {
        "definition": "plant",
        "language": "Finska"
      }
    ],
    "ken": [
      {
        "definition": "can",
        "language": "Tok Pisin"
      },
      {
        "definition": "can",
        "language": "Engelska"
      }
    ],
    "kepeken": [
      {
        "definition": "to use",
        "language": "Nederländska"
      }
    ],
    "kijetesantakalu": [
      {
        "definition": "kinkajou",
        "language": "Finska"
      }
    ],
    "kiki": [
      {
        "language": "a priori"
      }
    ],
    "kili": [
      {
        "definition": "fruit",
        "language": "Georgiska"
      }
    ],
    "kin": [
      {
        "definition": "too, also, still",
        "language": "Finska"
      }
    ],
    "kipisi": [
      {
        "definition": "to cut (intransitive)",
        "language": "Inuktitut"
      }
    ],
    "kiwen": [
      {
        "definition": "stone (genitive case)",
        "language": "Finska"
      }
    ],
    "ko": [
      {
        "definition": "cream, paste",
        "language": "Kantonesiska"
      }
    ],
    "kokosila": [
      {
        "definition": "to speak among Esperantists in a language other than Esperanto",
        "language": "Esperanto"
      },
      {
        "definition": "crocodile",
        "language": "Esperanto"
      }
    ],
    "kon": [
      {
        "definition": "air, atmosphere, ambience, opinion",
        "language": "Mandarin"
      }
    ],
    "konwe": [
      {
        "definition": "John Conway, creator of The Game of Life",
        "language": "Engelska"
      },
      {
        "definition": "kon wile",
        "language": "toki pona"
      }
    ],
    "ku": [
      {
        "language": "a priori"
      }
    ],
    "kule": [
      {
        "definition": "färg",
        "language": "Akadisk franska"
      }
    ],
    "kulijo": [
      {
        "definition": "coolio",
        "language": "Engelska"
      }
    ],
    "kulupu": [
      {
        "definition": "group",
        "language": "Tonganska"
      },
      {
        "definition": "group",
        "language": "Engelska"
      }
    ],
    "kute": [
      {
        "definition": "listen",
        "language": "Akadisk franska"
      }
    ],
    "la": [
      {
        "definition": "(definite article)",
        "language": "Esperanto"
      },
      {
        "definition": "(feminine singular definite article)",
        "language": "Romance"
      },
      {
        "definition": "(proximal & topical suffix)",
        "language": "Akadisk franska"
      }
    ],
    "lanpan": [
      {
        "definition": "take, seize, grasp, receive",
        "language": "Greek"
      }
    ],
    "lape": [
      {
        "definition": "sleep",
        "language": "Nederländska"
      }
    ],
    "laso": [
      {
        "definition": "blue, inexperienced",
        "language": "Welsh"
      },
      {
        "definition": "green, blue",
        "language": "Proto-Brythonic"
      }
    ],
    "lawa": [
      {
        "definition": "head",
        "language": "Serbokroatiska"
      }
    ],
    "leko": [
      {
        "definition": "Lego",
        "language": "Engelska"
      },
      {
        "definition": "play well",
        "language": "Danska"
      },
      {
        "definition": "block, section",
        "language": "Finska"
      }
    ],
    "len": [
      {
        "definition": "clothing",
        "language": "Akadisk franska"
      }
    ],
    "lete": [
      {
        "definition": "cold",
        "language": "Akadisk franska"
      },
      {
        "definition": "cold",
        "language": "Old French"
      }
    ],
    "li": [
      {
        "definition": "he",
        "language": "Esperanto"
      },
      {
        "definition": "he",
        "language": "Latin"
      },
      {
        "definition": "he",
        "language": "Tok Pisin"
      },
      {
        "definition": "he",
        "language": "Engelska"
      }
    ],
    "lili": [
      {
        "definition": "small, little",
        "language": "Tok Pisin"
      },
      {
        "definition": "small, little",
        "language": "Ramoaaina"
      }
    ],
    "linja": [
      {
        "definition": "line",
        "language": "Finska"
      },
      {
        "definition": "line",
        "language": "Fornsvenska"
      }
    ],
    "linluwi": [
      {
        "definition": "internet",
        "language": "Welsh"
      }
    ],
    "lipu": [
      {
        "definition": "flag, banner, ticket",
        "language": "Finska"
      }
    ],
    "loje": [
      {
        "definition": "red (inflected)",
        "language": "Nederländska"
      }
    ],
    "lon": [
      {
        "definition": "at, in, on, (spacial particle)",
        "language": "Tok Pisin"
      },
      {
        "definition": "along",
        "language": "Engelska"
      }
    ],
    "luka": [
      {
        "definition": "hand, arm",
        "language": "Serbokroatiska"
      }
    ],
    "lukin": [
      {
        "definition": "see, look at",
        "language": "Tok Pisin"
      },
      {
        "definition": "look",
        "language": "Engelska"
      },
      {
        "definition": "him",
        "language": "Engelska"
      }
    ],
    "lupa": [
      {
        "definition": "loop",
        "language": "Lojban"
      },
      {
        "definition": "loop",
        "language": "Mandarin"
      },
      {
        "definition": "loop",
        "language": "Engelska"
      },
      {
        "definition": "loop",
        "language": "Hindi"
      },
      {
        "definition": "loop",
        "language": "Arabic"
      }
    ],
    "ma": [
      {
        "definition": "earth, land",
        "language": "Finska"
      }
    ],
    "majuna": [
      {
        "definition": "old (not young)",
        "language": "Esperanto"
      },
      {
        "definition": "bad",
        "language": "Latin"
      },
      {
        "definition": "young",
        "language": "German"
      },
      {
        "definition": "young",
        "language": "Franska"
      }
    ],
    "mama": [
      {
        "definition": "father",
        "language": "Georgiska"
      }
    ],
    "mani": [
      {
        "definition": "money",
        "language": "Engelska"
      },
      {
        "definition": "livestock",
        "language": "Proto-Germanic"
      },
      {
        "definition": "cattle",
        "language": "Latin"
      }
    ],
    "meli": [
      {
        "definition": "woman, wife, feminine",
        "language": "Tok Pisin"
      },
      {
        "definition": "pretty",
        "language": "Tolai"
      },
      {
        "definition": "Mary",
        "language": "Engelska"
      }
    ],
    "melome": [
      {
        "definition": "women loving women",
        "language": "toki pona"
      }
    ],
    "meso": [
      {
        "definition": "middle",
        "language": "Greek"
      }
    ],
    "mi": [
      {
        "definition": "I, me",
        "language": "Esperanto"
      },
      {
        "definition": "(1st person singular oblique)",
        "language": "Romance"
      }
    ],
    "mije": [
      {
        "definition": "man, husband",
        "language": "Finska"
      }
    ],
    "mijomi": [
      {
        "definition": "men loving men",
        "language": "toki pona"
      }
    ],
    "misa": [
      {
        "definition": "mouse (diminutive)",
        "language": "Ukrainian"
      }
    ],
    "misikeke": [
      {
        "definition": "medicine, drug",
        "language": "Ojibwa"
      }
    ],
    "moku": [
      {
        "definition": "munching",
        "language": "Japanska"
      }
    ],
    "moli": [
      {
        "definition": "die",
        "language": "Akadisk franska"
      }
    ],
    "monsi": [
      {
        "definition": "my ass (vulgar)",
        "language": "Akadisk franska"
      }
    ],
    "monsuta": [
      {
        "definition": "monster",
        "language": "Japanska"
      },
      {
        "definition": "monster",
        "language": "Engelska"
      }
    ],
    "mu": [
      {
        "language": "onomatopoetiskt"
      }
    ],
    "mulapisu": [
      {
        "language": "a priori"
      }
    ],
    "mun": [
      {
        "definition": "moon",
        "language": "Engelska"
      }
    ],
    "musi": [
      {
        "definition": "amuse, entertain",
        "language": "Esperanto"
      },
      {
        "definition": "amuse, entertain",
        "language": "Franska"
      }
    ],
    "mute": [
      {
        "definition": "a lot",
        "language": "Esperanto"
      },
      {
        "definition": "a lot",
        "language": "Latin"
      }
    ],
    "n": [
      {
        "language": "onomatopoetiskt"
      }
    ],
    "namako": [
      {
        "definition": "salt",
        "language": "Hindi"
      },
      {
        "definition": "salt",
        "language": "Persian"
      }
    ],
    "nanpa": [
      {
        "definition": "number",
        "language": "Tok Pisin"
      },
      {
        "definition": "number",
        "language": "Engelska"
      }
    ],
    "nasa": [
      {
        "definition": "dunderhead",
        "language": "Tok Pisin"
      }
    ],
    "nasin": [
      {
        "definition": "way, method",
        "language": "Serbokroatiska"
      }
    ],
    "nena": [
      {
        "definition": "nose",
        "language": "Finska"
      }
    ],
    "ni": [
      {
        "definition": "this",
        "language": "Kantonesiska"
      },
      {
        "definition": "(continuation of a state/action)",
        "language": "Tai"
      }
    ],
    "nimi": [
      {
        "definition": "name",
        "language": "Finska"
      }
    ],
    "nimisin": [
      {
        "definition": "new word",
        "language": "toki pona"
      }
    ],
    "nja": [
      {
        "definition": "meow (onomatopoeia)",
        "language": "Japanska"
      }
    ],
    "noka": [
      {
        "definition": "foot, leg",
        "language": "Serbokroatiska"
      }
    ],
    "o": [
      {
        "definition": "(vocative suffix)",
        "language": "Georgiska"
      }
    ],
    "ojuta": [
      {
        "definition": "'lick my balls' (same as English 'ligma balls')",
        "language": "toki pona"
      }
    ],
    "oke": [
      {
        "definition": "okay",
        "language": "Engelska"
      }
    ],
    "oko": [
      {
        "definition": "eye",
        "language": "Serbokroatiska"
      }
    ],
    "olin": [
      {
        "definition": "I love",
        "language": "Serbokroatiska"
      }
    ],
    "omekapo": [
      {
        "definition": "'eat a good fish', wishing somebody well",
        "language": "toki pona"
      }
    ],
    "ona": [
      {
        "definition": "she",
        "language": "Serbokroatiska"
      }
    ],
    "open": [
      {
        "definition": "open",
        "language": "Engelska"
      }
    ],
    "owe": [
      {
        "definition": "George Orwell, author of 1984",
        "language": "Engelska"
      }
    ],
    "pakala": [
      {
        "definition": "accident",
        "language": "Tok Pisin"
      },
      {
        "definition": "bugger up",
        "language": "Engelska"
      }
    ],
    "pake": [
      {
        "definition": "block",
        "language": "Engelska"
      }
    ],
    "pakola": [
      {
        "definition": "broken, damaged, harmed, destroyed",
        "language": "toki pona"
      }
    ],
    "pali": [
      {
        "definition": "do, make",
        "language": "Esperanto"
      }
    ],
    "palisa": [
      {
        "definition": "bat, rod, cane",
        "language": "Serbokroatiska"
      }
    ],
    "pan": [
      {
        "definition": "bread",
        "language": "Romance"
      },
      {
        "definition": "bread",
        "language": "Japanska"
      },
      {
        "definition": "bread",
        "language": "Portuguese"
      }
    ],
    "pana": [
      {
        "definition": "put, set, place",
        "language": "Finska"
      },
      {
        "definition": "give to each other",
        "language": "swahili"
      }
    ],
    "penpo": [
      {
        "definition": "only toki pona",
        "language": "toki pona"
      }
    ],
    "pi": [
      {
        "definition": "of",
        "language": "Tok Pisin"
      },
      {
        "definition": "belong",
        "language": "Engelska"
      }
    ],
    "pika": [
      {
        "definition": "Pikachū, an electric Pokémon",
        "language": "Japanska"
      }
    ],
    "pilin": [
      {
        "definition": "feel",
        "language": "Tok Pisin"
      },
      {
        "definition": "him",
        "language": "Engelska"
      },
      {
        "definition": "him",
        "language": "Engelska"
      }
    ],
    "pimeja": [
      {
        "definition": "dark",
        "language": "Finska"
      }
    ],
    "pini": [
      {
        "definition": "finished, completed",
        "language": "Akadisk franska"
      },
      {
        "definition": "finish (perfective aspect)",
        "language": "Tok Pisin"
      },
      {
        "definition": "finish",
        "language": "Engelska"
      }
    ],
    "pipi": [
      {
        "definition": "bug",
        "language": "Akadisk franska"
      }
    ],
    "po": [
      {
        "definition": "(number) four",
        "language": "Engelska"
      }
    ],
    "poka": [
      {
        "definition": "side, flank (genitive)",
        "language": "Serbokroatiska"
      }
    ],
    "poki": [
      {
        "definition": "box, female genitalia (vulgar)",
        "language": "Tok Pisin"
      },
      {
        "definition": "box",
        "language": "Engelska"
      }
    ],
    "pona": [
      {
        "definition": "good",
        "language": "Esperanto"
      }
    ],
    "powe": [
      {
        "definition": "not true",
        "language": "Akadisk franska"
      }
    ],
    "pu": [
      {
        "definition": "unworked wood, sincere, honest, inherent quality, simple",
        "language": "Mandarin"
      },
      {
        "definition": "book",
        "language": "Engelska"
      }
    ],
    "puwa": [
      {
        "definition": "fluffy things (onomatopoeia)",
        "language": "Japanska"
      }
    ],
    "sama": [
      {
        "definition": "same",
        "language": "Finska"
      },
      {
        "definition": "same, alike",
        "language": "Proto-Germanic"
      },
      {
        "definition": "same",
        "language": "Esperanto"
      },
      {
        "definition": "same",
        "language": "Engelska"
      }
    ],
    "san": [
      {
        "definition": "(number) three",
        "language": "Japanska"
      },
      {
        "definition": "(number) three",
        "language": "Kantonesiska"
      },
      {
        "definition": "(number) three",
        "language": "Kantonesiska"
      }
    ],
    "seli": [
      {
        "definition": "hot",
        "language": "Georgiska"
      }
    ],
    "selo": [
      {
        "definition": "skin, peel",
        "language": "Esperanto"
      },
      {
        "definition": "peel, husk, shell",
        "language": "German"
      }
    ],
    "seme": [
      {
        "definition": "what, something",
        "language": "Mandarin"
      }
    ],
    "sewi": [
      {
        "definition": "upwards",
        "language": "Georgiska"
      }
    ],
    "sijelo": [
      {
        "definition": "body",
        "language": "Serbokroatiska"
      }
    ],
    "sike": [
      {
        "definition": "circle",
        "language": "Engelska"
      }
    ],
    "sin": [
      {
        "definition": "new, fresh",
        "language": "Mandarin"
      }
    ],
    "sina": [
      {
        "definition": "(pronoun) you, y'all",
        "language": "Finska"
      }
    ],
    "sinpin": [
      {
        "definition": "in front",
        "language": "Kantonesiska"
      }
    ],
    "sitelen": [
      {
        "definition": "paint",
        "language": "Nederländska"
      }
    ],
    "soko": [
      {
        "definition": "mushroom",
        "language": "Georgiska"
      }
    ],
    "sona": [
      {
        "definition": "knowledge",
        "language": "Georgiska"
      }
    ],
    "soto": [
      {
        "definition": "left side",
        "language": "swahili"
      }
    ],
    "soweli": [
      {
        "definition": "beastly animal, lively, passionate",
        "language": "Georgiska"
      }
    ],
    "su": [
      {
        "language": "a priori"
      }
    ],
    "suli": [
      {
        "definition": "big, large, great",
        "language": "Finska"
      }
    ],
    "suno": [
      {
        "definition": "sun",
        "language": "Esperanto"
      }
    ],
    "supa": [
      {
        "definition": "surface",
        "language": "Esperanto"
      },
      {
        "definition": "surface",
        "language": "Akadisk franska"
      },
      {
        "definition": "surface",
        "language": "Engelska"
      }
    ],
    "sutopatikuna": [
      {
        "definition": "platypus, (literally) strange beak",
        "language": "Serbokroatiska"
      }
    ],
    "suwi": [
      {
        "definition": "sweet",
        "language": "Tok Pisin"
      },
      {
        "definition": "sweet",
        "language": "Engelska"
      }
    ],
    "taki": [
      {
        "definition": "the sound of two magnets hitting each other (onomatopoeia)",
        "language": "Koreanska"
      }
    ],
    "tan": [
      {
        "definition": "from",
        "language": "Kantonesiska"
      }
    ],
    "taso": [
      {
        "definition": "just, only, but, however",
        "language": "Tok Pisin"
      },
      {
        "definition": "that’s all",
        "language": "Engelska"
      }
    ],
    "tawa": [
      {
        "definition": "toward",
        "language": "Engelska"
      }
    ],
    "te": [
      {
        "definition": "(quotative)",
        "language": "Japanska"
      }
    ],
    "teje": [
      {
        "definition": "right",
        "language": "Welsh"
      }
    ],
    "telo": [
      {
        "definition": "(some) water",
        "language": "Akadisk franska"
      }
    ],
    "tenpo": [
      {
        "definition": "tid",
        "language": "Esperanto"
      },
      {
        "definition": "tid",
        "language": "Latin"
      }
    ],
    "to": [
      {
        "definition": "(quotative)",
        "language": "Japanska"
      }
    ],
    "toki": [
      {
        "definition": "talk",
        "language": "Tok Pisin"
      },
      {
        "definition": "talk",
        "language": "Engelska"
      }
    ],
    "tomo": [
      {
        "definition": "house",
        "language": "Esperanto"
      },
      {
        "definition": "house",
        "language": "Polish"
      },
      {
        "definition": "house",
        "language": "Latin"
      },
      {
        "definition": "house",
        "language": "Klassisk grekiska"
      }
    ],
    "tonsi": [
      {
        "definition": "comrade (same will/purpose), LGBT+",
        "language": "Mandarin"
      }
    ],
    "tu": [
      {
        "definition": "two",
        "language": "Engelska"
      },
      {
        "definition": "two",
        "language": "Esperanto"
      }
    ],
    "unpa": [
      {
        "language": "onomatopoetiskt"
      }
    ],
    "unu": [
      {
        "definition": "lila, violett",
        "language": "Malay-Indonesian"
      }
    ],
    "usawi": [
      {
        "definition": "witchcraft, sorcery",
        "language": "swahili"
      }
    ],
    "uta": [
      {
        "definition": "mouth",
        "language": "Serbokroatiska"
      }
    ],
    "utala": [
      {
        "definition": "strike, hit, beat",
        "language": "Serbokroatiska"
      }
    ],
    "wa": [
      {
        "language": "onomatopoetiskt"
      }
    ],
    "walo": [
      {
        "definition": "white",
        "language": "Finska"
      }
    ],
    "wan": [
      {
        "definition": "one",
        "language": "Engelska"
      }
    ],
    "waso": [
      {
        "definition": "bird",
        "language": "Akadisk franska"
      }
    ],
    "wasoweli": [
      {
        "definition": "bird, flying creature",
        "language": "toki pona"
      },
      {
        "definition": "land animal, fuzzy creature",
        "language": "toki pona"
      }
    ],
    "wawa": [
      {
        "definition": "strong, powerful, thick",
        "language": "Finska"
      }
    ],
    "weka": [
      {
        "definition": "away, gone",
        "language": "Nederländska"
      }
    ],
    "wekama": [
      {
        "definition": "'leave-arrive', to leave and come back",
        "language": "toki pona"
      }
    ],
    "wile": [
      {
        "definition": "want, desire",
        "language": "Nederländska"
      }
    ],
    "wuwojiti": [
      {
        "definition": "(sound)",
        "language": "toki pona"
      },
      {
        "definition": "(sound)",
        "language": "toki pona"
      },
      {
        "definition": "(sound)",
        "language": "toki pona"
      },
      {
        "definition": "(sound)",
        "language": "toki pona"
      }
    ],
    "yupekosi": [
      {
        "language": "a priori"
      }
    ]
  },
  "sp_etymology": {
    "a": "exclamation radical + Latin lowercase letter A; radical from exclamation point (!), without the full stop at the bottom. compare o",
    "akesi": "animal radical; pictogram of a lizard. radical represents eyes",
    "ala": "X mark, a crosslinguistic symbol for negation",
    "alasa": "pictogram of a bow and an arrow",
    "ale": "infinity symbol (∞)",
    "ali": "infinity symbol (∞)",
    "anpa": "location radical + \"container\"; the latter perhaps from a truncated square for a general object (compare sinpin) or a container (compare poki). for the radical, see also how dots are used in blissymbols; compare blissymbol \"below\"",
    "ante": "perhaps alteration from sama, or a combination of sama and ala. perhaps an ideogram representing a diversion of two lines",
    "anu": "perhaps from mathematical symbol \"or\" (∨)",
    "apeja": "",
    "awen": "motion radical; legs facing against each other, implying standing",
    "e": "",
    "en": "from plus sign (+); compare blissymbol “and”.",
    "epiku": "pona with emitters; [alternate] rotated ni",
    "esun": "not from a currency symbol (sonja confirmed; said “i think that one is from Mikmaq” but couldn't find a mikmaq symbol similar to it).",
    "ijo": "a circle, for a general object",
    "ike": "pictogram of a frowning mouth. compare pona",
    "ilo": "perhaps a pictogram of a hammer",
    "insa": "location radical + “container”; compare blissymbol “in”",
    "isipin": "",
    "jaki": "a scribble",
    "jami": "",
    "jan": "head radical; pictogram of a person showing the shoulders",
    "jasima": "",
    "jelo": "color radical + suno",
    "jo": "perhaps a pictogram of a person pointing at themself or holding something",
    "jonke": "",
    "kala": "pictogram of a fish",
    "kalama": "“mouth” (or dotless uta) with emitters",
    "kama": "motion radical; legs facing to the left. compare tawa and blissymbol “walk”",
    "kamalawala": "circle-A, an anarchy symbol",
    "kapesi": "",
    "kasi": "pictogram of a sprout",
    "ken": "perhaps from Latin letter K",
    "kepeken": "hand modifier + ilo",
    "kijetesantakalu": "a drawing of a raccoon with a tail",
    "kiki": "",
    "kili": "pictogram of a fruit, perhaps an apple",
    "kin": "",
    "kipisi": "",
    "kiwen": "pictogram of a rock or a gem",
    "ko": "pictogram of splashed goo",
    "kokosila": "",
    "kon": "ideogram; wavy lines to indicate the fluidity of gas. compare telo",
    "konwe": "pictogram of a glider in Conway's Game of Life, a machine which moves across the game board.",
    "ku": "pictogram of the front cover of “Toki Pona Dictionary”, depicting a jacket with a toki pona patch.",
    "kule": "color radical; perhaps the horizontal line indicates the sense of “the concept itself”. or perhaps a pictogram of light passing through a prism (color radical)",
    "kulijo": "",
    "kulupu": "pictogram of a group consisting of three members represented by circles",
    "kute": "pictogram of an ear. compare blissymbol “ear”",
    "la": "perhaps related to blissymbol “later” and “ago”, or perhaps a parenthesis",
    "lanpan": "",
    "lape": "pictogram of a lying person",
    "laso": "color radical + kasi",
    "lawa": "head radical; perhaps the horizontal line for the same reason as in kule. alternatively perhaps a pictogram of a person wearing a cap",
    "leko": "",
    "len": "perhaps a pictogram of a piece of fabric",
    "lete": "pictogram of a snowflake",
    "li": "",
    "lili": "ideogram showing smaller size compared to suli",
    "linja": "pictogram of a string",
    "linluwi": "",
    "lipu": "pictogram of a sheet of paper. compare blissymbol “paper”",
    "loje": "color radical + “mouth”",
    "lon": "location radical above a line. compare blissymbol “over”",
    "luka": "pictogram of a hand",
    "lukin": "pictogram of an eye. compare blissymbol “eye”",
    "lupa": "pictogram of a concave surface. compare nena",
    "ma": "perhaps from modern astronomical symbol “earth” (⊕)",
    "majuna": "",
    "mama": "head radical; perhaps the smaller circle representing the child",
    "mani": "a pictogram of a large domestic animal, such as a cow (sonja confirmed)",
    "meli": "head radical with long hair",
    "melome": "",
    "meso": "",
    "mi": "perhaps a hand pointing towards the speaker. compare sina and ona",
    "mije": "head radical with perhaps wide shoulders. compare jan",
    "mijomi": "",
    "misa": "",
    "misikeke": "",
    "moku": "hand modifier + “mouth”",
    "moli": "head radical; a dead person, represented by the crossed eyes",
    "monsi": "location radical + rotate “container”. compare sinpin",
    "monsuta": "visual representation of shaking as seen in cartoons",
    "mu": "pictogram of a mammal",
    "mulapisu": "",
    "mun": "pictogram of a crescent moon. compare blissymbol “moon”",
    "musi": "perhaps a pictogram of a smile with rosy cheeks or a lyre",
    "mute": "ideogram consisting of three tally marks. compare wan and tu",
    "n": "exclamation radical with the lowercase letter “n”",
    "namako": "",
    "nanpa": "from number sign (#). compare blissymbol “number”",
    "nasa": "perhaps spiral representing “dizziness”, as can be commonly seen in Japanese manga and anime",
    "nasin": "ideogram consisting of an arrow along a vertical line",
    "nena": "pictogram of a convex surface. compare lupa",
    "ni": "en pil",
    "nimi": "perhaps a pictogram of a nametag or sitelen pona cartouche",
    "nimisin": "",
    "nja": "",
    "noka": "pictogram of a foot with an ankle",
    "o": "exclamation radical + Latin lowercase letter O. compare a",
    "ojuta": "",
    "oke": "",
    "oko": "eye from a side",
    "olin": "two heart symbols (♡), perhaps to distinguish from pilin. [alternate] pilin with emitters",
    "omekapo": "",
    "ona": "perhaps a hand pointing sideways. compare mi and sina",
    "open": "perhaps a pictogram of an opened container",
    "owe": "lukin (or an eye) with emitters",
    "pakala": "pictogram of a cracked object",
    "pake": "",
    "pakola": "",
    "pali": "hand modifier + ijo",
    "palisa": "pictogram of a stick",
    "pan": "perhaps a pictogram of a grain crop",
    "pana": "luka with emitters",
    "penpo": "toki-pona with omnidirectional emitters",
    "pi": "perhaps from tilted blissymbol “by”",
    "pika": "",
    "pilin": "from heart symbol (♡). compare blissymbol “feeling”",
    "pimeja": "color radical; perhaps the cross representing the absence of light",
    "pini": "perhaps a blocking wall",
    "pipi": "animal radical; pictogram of a bug",
    "po": "Arabic numeral 4",
    "poka": "location radical + “container”",
    "poki": "pictogram of a container",
    "pona": "pictogram of a smiling mouth. compare ike",
    "powe": "",
    "pu": "pictogram of the cover of the book “Toki Pona: The Language of Good”. alternatively a semantic compound glyph of lipu and toki pona",
    "puwa": "",
    "sama": "from equal sign (=). compare blissymbol “same”",
    "san": "",
    "seli": "perhaps a pictogram of a lit campfire or a simplified pictogram of a fire",
    "selo": "",
    "seme": "from question mark (?). compare blissymbol “what”",
    "sewi": "från arabiska ١ّللَه‎ \"allah\"",
    "sijelo": "perhaps a pictogram of a torso",
    "sike": "two circles, perhaps to distinguish from ijo. alternatively outline of a thick empty circle",
    "sin": "",
    "sina": "perhaps a hand pointing towards the listener. compare mi and ona",
    "sinpin": "location radical + rotate “container”. compare monsi",
    "sitelen": "perhaps a representation of symbols on a piece of paper (lipu)",
    "soko": "pictogram of a mushroom",
    "sona": "lipu with emitters",
    "soto": "",
    "soweli": "animal radical; pictogram of a mammal",
    "su": "pictogram of the front cover of The Wizard of Oz illustrated story book, depicting the yellow brick road from the story",
    "suli": "ideogram showing bigger size compared to lili",
    "suno": "pictogram of the sun",
    "supa": "pictogram of a table. compare blissymbol “table”",
    "sutopatikuna": "",
    "suwi": "perhaps a pictogram of a smiling face",
    "taki": "",
    "tan": "a leaping arrow pointing from right to left, implying derivation or cause",
    "taso": "from blissymbol “but”",
    "tawa": "motion radical; legs facing to the right. compare kama and blissymbol “walk”",
    "te": "",
    "teje": "",
    "telo": "pictogram of wave. compare blissymbol “water”",
    "tenpo": "piktogram av en klocka. jämför blissymbolen för \"tid\"",
    "to": "",
    "toki": "emitters + ijo or a general circle",
    "tomo": "pictogram of a house. compare blissymbol “house”",
    "tonsi": "",
    "tu": "two tally marks. compare mute and wan",
    "unpa": "perhaps a derivation of heart symbol (especially visible from the original drawing of the character), or a knot pattern implying intercourse, or perhaps a pictogram of a genitalia",
    "unu": "",
    "usawi": "nasa with emitters",
    "uta": "“mouth” with a dot below",
    "utala": "perhaps from crossed swords symbol (⚔️)",
    "wa": "",
    "walo": "color radical; perhaps the reverse of pimeja, the color radical cutting of the cross instead of vice versa",
    "wan": "one tally mark or Indo-Arabic numeral 1, perhaps to make it more distinct",
    "waso": "animal radical; pictogram of a bird",
    "wasoweli": "",
    "wawa": "perhaps a pictogram of a person with raised arms, to signify strength",
    "weka": "“poof lines”; indicating the movement of something disappearing",
    "wekama": "",
    "wile": "perhaps from Latin letter W",
    "wuwojiti": "",
    "yupekosi": ""
  }
}